mediacurator/__init__.py
mediacurator/mediacurator.py
mediacurator/library/__init__.py
mediacurator/library/medialibrary.py
mediacurator/library/tools.py
mediacurator/library/video.py
mediacurator/tests/__init__.py
mediacurator-1.0.1.dist-info/LICENSE
mediacurator-1.0.1.dist-info/METADATA
mediacurator-1.0.1.dist-info/WHEEL
mediacurator-1.0.1.dist-info/entry_points.txt
mediacurator-1.0.1.dist-info/top_level.txt
mediacurator-1.0.1.dist-info/zip-safe
mediacurator-1.0.1.dist-info/RECORD
