Metadata-Version: 2.1
Name: mediacurator
Version: 1.0.1
Summary: mediacurator is a Python command line tool to manage a media database.
Home-page: https://github.com/fabquenneville/mediacurator
Download-URL: https://pypi.python.org/pypi/mediacurator
Author: Fabrice Quenneville
Author-email: fab@fabq.ca
License: GPL-3.0
Project-URL: Bug Tracker, https://github.com/fabquenneville/mediacurator/issues
Project-URL: Documentation, https://fabquenneville.github.io/mediacurator/
Project-URL: Source Code, https://github.com/fabquenneville/mediacurator
Keywords: codecs,filters,video,x265,av1,media-database,python-command,hevc,multimedia,video-processing
Platform: any
Classifier: Topic :: Multimedia :: Video :: Conversion
Classifier: Development Status :: 5 - Production/Stable
Classifier: Intended Audience :: End Users/Desktop
Classifier: Natural Language :: English
Classifier: Programming Language :: Python :: 3.6
Classifier: Programming Language :: Python :: 3.7
Classifier: Programming Language :: Python :: 3.8
Classifier: Programming Language :: Python :: 3.9
Classifier: Programming Language :: Python :: 3.10
Classifier: Programming Language :: Python :: 3.11
Classifier: Programming Language :: Python :: 3.12
Classifier: License :: OSI Approved :: GNU General Public License v3 (GPLv3)
Classifier: Operating System :: OS Independent
Classifier: Environment :: Console
Requires-Python: >=3.6
License-File: LICENSE
Requires-Dist: argcomplete
Requires-Dist: colorama
Requires-Dist: pathlib
